agent_relay/__init__.py
agent_relay/context.py
agent_relay/db.py
agent_relay/runtime.py
agent_relay/schema.py
agent_relay/tooling.py
agentrelay-0.1.1.dist-info/METADATA
agentrelay-0.1.1.dist-info/WHEEL
agentrelay-0.1.1.dist-info/licenses/LICENSE.txt
agentrelay-0.1.1.dist-info/RECORD
