Metadata-Version: 2.4
Name: agentrelay
Version: 0.1.1
Summary: Framework-agnostic transactional agent runtime with idempotent tool calls, saga compensations, and deterministic replay.
Project-URL: Homepage, https://github.com/YalmanchiliTejas/agenttrail
Project-URL: Repository, https://github.com/YalmanchiliTejas/agenttrail
Project-URL: Issues, https://github.com/YalmanchiliTejas/agenttrail/issues
Author: Tejas Yalamanchili
License: MIT License
License-File: LICENSE.txt
Keywords: agents,ai,idempotency,llm,orchestration,saga,workflow
Classifier: Development Status :: 3 - Alpha
Classifier: Intended Audience :: Developers
Classifier: License :: OSI Approved :: MIT License
Classifier: Programming Language :: Python
Classifier: Programming Language :: Python :: 3.10
Classifier: Programming Language :: Python :: 3.11
Classifier: Programming Language :: Python :: 3.12
Classifier: Topic :: Software Development :: Libraries
Classifier: Topic :: System :: Distributed Computing
Requires-Python: >=3.10
Requires-Dist: pymysql>=1.1.0
Requires-Dist: sqlalchemy>=2.0.0
Provides-Extra: dev
Requires-Dist: mypy>=1.8.0; extra == 'dev'
Requires-Dist: pytest>=8.0.0; extra == 'dev'
